dpam/__init__.py
dpam/dpam.py
dpam/helper.py
dpam/network_model.py
dpam/setup.py
dpam/pre-model/finetune_loss/my_test_model.data-00000-of-00001
dpam/pre-model/finetune_loss/my_test_model.index
dpam/pre-model/finetune_loss/my_test_model.meta
dpam/pre-model/linear_layer_loss/my_test_model.data-00000-of-00001
dpam/pre-model/linear_layer_loss/my_test_model.index
dpam/pre-model/linear_layer_loss/my_test_model.meta
dpam/pre-model/pretrained_loss/loss_model.ckpt.data-00000-of-00001
dpam/pre-model/pretrained_loss/loss_model.ckpt.index
dpam/pre-model/pretrained_loss/loss_model.ckpt.meta
dpam/pre-model/scratch_loss/my_test_model.data-00000-of-00001
dpam/pre-model/scratch_loss/my_test_model.index
dpam/pre-model/scratch_loss/my_test_model.meta
dpam/pre-model/se_model/se_model.ckpt.data-00000-of-00001
dpam/pre-model/se_model/se_model.ckpt.index
dpam/pre-model/se_model/se_model.ckpt.meta
dpam_test/__init__.py
dpam_test/dpam.py
dpam_test/helper.py
dpam_test/models.py
dpam_test/network_model.py
pip_pasm/__init__.py
pip_pasm/helper.py
pip_pasm/network_model.py
pip_pasm/pip_pasm.py
pip_pasm/setup.py
dpam-0.0.4.dist-info/LICENSE
dpam-0.0.4.dist-info/METADATA
dpam-0.0.4.dist-info/WHEEL
dpam-0.0.4.dist-info/top_level.txt
dpam-0.0.4.dist-info/RECORD
