Metadata-Version: 2.1
Name: dpam
Version: 0.0.4
Summary: A pip package for perceptual audio metric
Home-page: https://github.com/pranaymanocha/PerceptualAudio
Author: Pranay Manocha
Author-email: pranaymnch@gmail.com
License: UNKNOWN
Platform: UNKNOWN
Classifier: License :: OSI Approved :: MIT License
Classifier: Operating System :: OS Independent
